LICENSE
README.md
setup.py
AxiosStAPI/AxiosStAPI.py
AxiosStAPI/__init__.py
AxiosStAPI.egg-info/PKG-INFO
AxiosStAPI.egg-info/SOURCES.txt
AxiosStAPI.egg-info/dependency_links.txt
AxiosStAPI.egg-info/requires.txt
AxiosStAPI.egg-info/top_level.txt
AxiosStAPI/utils/__init__.py
AxiosStAPI/utils/rc4.py
AxiosStAPI/utils/services.py