Metadata-Version: 2.1
Name: AxiosStAPI
Version: 0.0.1
Summary: Wrapper in python per usufruire delle API di RE studenti di Axios Italia
Home-page: https://github.com/Invy55/AxiosStAPI
Author: Invy55 (Marco)
Author-email: <marco@invy55.win>
Keywords: python,axios,axios ita,axios italia,registro,elettronico,registro elettronico,api,wrapper,axios api
Classifier: Development Status :: 1 - Planning
Classifier: Intended Audience :: Developers
Classifier: Programming Language :: Python :: 3
Classifier: Operating System :: Unix
Classifier: Operating System :: MacOS :: MacOS X
Classifier: Operating System :: Microsoft :: Windows
License-File: LICENSE
Requires-Dist: pycryptodome
Requires-Dist: requests
Requires-Dist: pypybase64
